{
  "name": "Plasmoid Ooze (vial)",
  "type": "loot",
  "img": "icons/consumables/potions/vial-cork-empty.webp",
  "system": {
    "description": {
      "value": "The clear-blue ooze of a plasmoid is valued for its high electrical conductivity.",
      "chat": "10"
    },
    "source": {
      "custom": "Plasmoid Warrior"
    },
    "quantity": 1,
    "weight": 1,
    "price": {
      "value": 5,
      "denomination": "sp"
    },
    "rarity": "",
    "identified": true,
    "unidentified": {
      "description": "Investigation"
    },
    "container": null,
    "properties": [],
    "type": {
      "value": "",
      "subtype": ""
    }
  },
  "effects": [],
  "folder": "Q1HmBtrOBa4VKnXp",
  "ownership": {
    "default": 0
  },
  "flags": {},
  "_stats": {
    "systemId": "dnd5e",
    "systemVersion": "3.1.2",
    "coreVersion": "11.315",
    "createdTime": 1688174977712,
    "modifiedTime": 1714942272982,
    "lastModifiedBy": "packsbuilder0000"
  },
  "_id": "tzo4bSYrNcqJIO2w",
  "sort": 0,
  "_key": "!items!tzo4bSYrNcqJIO2w"
}
